myPythonPackage/__init__.py
myPythonPackage/hello.py
DeanWoodward4TestingPythonPackage-0.1.dist-info/METADATA
DeanWoodward4TestingPythonPackage-0.1.dist-info/WHEEL
DeanWoodward4TestingPythonPackage-0.1.dist-info/top_level.txt
DeanWoodward4TestingPythonPackage-0.1.dist-info/RECORD
